feather/__init__.py
feather/component_factory.py
feather/components.py
feather/helpers.py
feather/featherlocal/publisher.py
feather/featherlocal/systemrunner.py
feather/featherlocal/webserver.py
feather/featherlocal/www/public/index.html
feather/featherlocal/www/public/main.js
feather/featherlocal/www/public/assets/android-chrome-144x144.png
feather/featherlocal/www/public/assets/android-chrome-192x192.png
feather/featherlocal/www/public/assets/android-chrome-256x256.png
feather/featherlocal/www/public/assets/android-chrome-36x36.png
feather/featherlocal/www/public/assets/android-chrome-384x384.png
feather/featherlocal/www/public/assets/android-chrome-48x48.png
feather/featherlocal/www/public/assets/android-chrome-512x512.png
feather/featherlocal/www/public/assets/android-chrome-72x72.png
feather/featherlocal/www/public/assets/android-chrome-96x96.png
feather/featherlocal/www/public/assets/apple-touch-icon-1024x1024.png
feather/featherlocal/www/public/assets/apple-touch-icon-114x114.png
feather/featherlocal/www/public/assets/apple-touch-icon-120x120.png
feather/featherlocal/www/public/assets/apple-touch-icon-144x144.png
feather/featherlocal/www/public/assets/apple-touch-icon-152x152.png
feather/featherlocal/www/public/assets/apple-touch-icon-167x167.png
feather/featherlocal/www/public/assets/apple-touch-icon-180x180.png
feather/featherlocal/www/public/assets/apple-touch-icon-57x57.png
feather/featherlocal/www/public/assets/apple-touch-icon-60x60.png
feather/featherlocal/www/public/assets/apple-touch-icon-72x72.png
feather/featherlocal/www/public/assets/apple-touch-icon-76x76.png
feather/featherlocal/www/public/assets/apple-touch-icon-precomposed.png
feather/featherlocal/www/public/assets/apple-touch-icon.png
feather/featherlocal/www/public/assets/apple-touch-startup-image-1125x2436.png
feather/featherlocal/www/public/assets/apple-touch-startup-image-1136x640.png
feather/featherlocal/www/public/assets/apple-touch-startup-image-1242x2208.png
feather-0.1.2.dist-info/LICENSE
feather-0.1.2.dist-info/METADATA
feather-0.1.2.dist-info/WHEEL
feather-0.1.2.dist-info/top_level.txt
feather-0.1.2.dist-info/RECORD
